edelweiss_data_cli/__main__.py
edelweiss_data_cli-0.1.0a2.dist-info/entry_points.txt
edelweiss_data_cli-0.1.0a2.dist-info/WHEEL
edelweiss_data_cli-0.1.0a2.dist-info/METADATA
edelweiss_data_cli-0.1.0a2.dist-info/RECORD
