Metadata-Version: 2.1
Name: edelweiss-data-cli
Version: 0.1.0a2
Summary: CLI client for EdelweissData
Home-page: https://github.com/DouglasConnect/edelweiss-data-cli-python
Author: Edelweiss Connect
Author-email: info@edelweissconnect.com
Requires-Python: >=3.6,<4.0
Classifier: Programming Language :: Python :: 3
Classifier: Programming Language :: Python :: 3.6
Classifier: Programming Language :: Python :: 3.7
Classifier: Programming Language :: Python :: 3.8
Requires-Dist: edelweiss-data (==0.2.19b0)
Project-URL: Documentation, https://github.com/DouglasConnect/edelweiss-data-cli-python
Project-URL: Repository, https://github.com/DouglasConnect/edelweiss-data-cli-python
